flask_mercury-1.1.10.dist-info/METADATA
flask_mercury-1.1.10.dist-info/RECORD
flask_mercury-1.1.10.dist-info/WHEEL
flask_mercury-1.1.10.dist-info/top_level.txt
mercury/__init__.py
mercury/api_model.py
mercury/doc_parser.py
mercury/exceptions.py
mercury/mercury_app.py
mercury/query_spec.py
mercury/utils.py
mercury/parameters/__init__.py
mercury/parameters/base.py
mercury/parameters/path/__init__.py
mercury/parameters/path/base.py
mercury/parameters/path/boolean.py
mercury/parameters/path/float_param.py
mercury/parameters/path/integer.py
mercury/parameters/path/string.py
mercury/parameters/path/uuid.py
mercury/parameters/query/__init__.py
mercury/parameters/query/base.py
mercury/parameters/query/boolean.py
mercury/parameters/query/float.py
mercury/parameters/query/float_param.py
mercury/parameters/query/integer.py
mercury/parameters/query/string.py
mercury/parameters/query/uuid.py
mercury/properties/__init__.py
mercury/properties/array_property.py
mercury/properties/base.py
mercury/properties/boolean_property.py
mercury/properties/date_property.py
mercury/properties/datetime_property.py
mercury/properties/dict_property.py
mercury/properties/file_property.py
mercury/properties/float_property.py
mercury/properties/integer_property.py
mercury/properties/object_property.py
mercury/properties/string_property.py
mercury/resource/__init__.py
mercury/resource/api_resource.py
mercury/resource/meta_resource.py
mercury/resource/flask/__init__.py
mercury/resource/flask/flask_resource.py
mercury/resource/flask/path_utils.py
mercury/resource/swagger/__init__.py
mercury/resource/swagger/path_utils.py
mercury/resource/swagger/swagger_resource.py
mercury/static/favicon-16x16.png
mercury/static/favicon-32x32.png
mercury/static/oauth2-redirect.html
mercury/static/swagger-ui-bundle.js
mercury/static/swagger-ui-bundle.js.map
mercury/static/swagger-ui-standalone-preset.js
mercury/static/swagger-ui-standalone-preset.js.map
mercury/static/swagger-ui.css
mercury/static/swagger-ui.css.map
mercury/static/swagger-ui.js
mercury/static/swagger-ui.js.map
mercury/static/templates/index.html
