Metadata-Version: 2.1
Name: flask-mercury
Version: 1.1.10
Summary: Flask-Mercury is a easy to used framework for implementing and documenting restful APIs based on flask and swagger.
Home-page: UNKNOWN
Author: Luis Felipe Muller
Author-email: luisfmuller@gmail.com
License: UNKNOWN
Keywords: Flask,Swagger,APIs,Rest
Platform: UNKNOWN
Requires-Dist: click (>=6.7)
Requires-Dist: flask-cors (>=3.0.6)
Requires-Dist: flask (>=1.0.2)
Requires-Dist: itsdangerous (>=0.24)
Requires-Dist: jinja2 (>=2.10)
Requires-Dist: markupsafe (>=1.0)
Requires-Dist: pytz (>=2018.5)
Requires-Dist: simple-mappers (>=1.0.3)
Requires-Dist: six (>=1.11.0)
Requires-Dist: werkzeug (>=0.14.1)
Requires-Dist: pyparsing (==2.3.0)
